galen/__init__.py
galen/spider/__init__.py
galen/spider/cookies.py
galen-0.1.4.dist-info/METADATA
galen-0.1.4.dist-info/WHEEL
galen-0.1.4.dist-info/top_level.txt
galen-0.1.4.dist-info/RECORD
