Metadata-Version: 2.1
Name: galen
Version: 0.1.4
Summary: Python spider tool collection
Home-page: https://github.com/rottengeek/garen
Author: rottengeek
Author-email: daituodi3@gmail.com
Classifier: Programming Language :: Python :: 3
Classifier: License :: OSI Approved :: MIT License
Classifier: Operating System :: OS Independent
Requires-Python: >=3.6
Requires-Dist: requests
